{
  "sections": {
    "image_banner_j8bDQb": {
      "type": "image-banner",
      "settings": {
        "image_2": "shopify:\/\/shop_images\/Tesla_Header_26aa7e22-14a0-459c-8f7d-bf7828b1ff8f.png",
        "image_overlay_opacity": 0,
        "underline": false,
        "hide_image_on_mobile": false,
        "image_height": "small",
        "desktop_content_position": "middle-right",
        "show_text_box": false,
        "desktop_content_alignment": "right",
        "color_scheme": "background-1",
        "image_behavior": "none",
        "mobile_content_alignment": "center",
        "stack_images_on_mobile": true,
        "show_text_below": false
      }
    },
    "divider_7njMcJ": {
      "type": "divider",
      "disabled": true,
      "custom_css": [
        "div {background: rgb(0, 180, 177); background: linear-gradient( 90deg, rgba(0, 180, 177, 1) 0%, rgba(184, 218, 121, 1) 100% ); height: 20px; min-width: 100%; margin: 0; padding: 0;}"
      ],
      "settings": {
        "divider_spacing": 0,
        "divider_border": false,
        "css_class": "",
        "custom_css": ""
      }
    },
    "rich_text_xFi7Um": {
      "type": "rich-text",
      "blocks": {
        "heading_R9ngj3": {
          "type": "heading",
          "settings": {
            "heading": "Building An equitable future",
            "heading_size": "h1"
          }
        },
        "text_7KFVLL": {
          "type": "text",
          "settings": {
            "text": "<p>We are dedicated to promoting social welfare and creating positive impacts in the communities where we operate. We are prioritizing the well-being, health, and safety of our employees and working towards fostering an inclusive and diverse workplace. We are supporting local initiatives and organizations that address social challenges and contribute to community development.<br\/><br\/><strong>Charitable Efforts:<\/strong><br\/>We continue to support causes that align with the work we do every day. Our team was able to donate a portion of our Evenflo.com sales to make a difference:<br\/>Safe Kids Worldwide® | Make a Wish® | Toys for Tots® | Operation Shower<\/p>"
          }
        }
      },
      "block_order": [
        "heading_R9ngj3",
        "text_7KFVLL"
      ],
      "settings": {
        "desktop_content_position": "center",
        "content_alignment": "center",
        "color_scheme": "background-1",
        "full_width": true,
        "padding_top": 40,
        "padding_bottom": 52
      }
    },
    "multicolumn_f9LYpV": {
      "type": "multicolumn",
      "blocks": {
        "column_RJWDbp": {
          "type": "column",
          "settings": {
            "image": "shopify:\/\/shop_images\/AdobeStock_671714083.png",
            "title": "Helping all children travel safely",
            "text": "<p>Evenflo engineers and safety professionals offer insight and experience to offer support for children with disabilities. In collaboration with nationally certified car seat technicians around the country, we evaluate, create and provide services to children and their families to help support their individual transportation needs. From short-term to long-term needs, we are here to help find a solution so all children can travel safely. <br\/>· Just this year, we announced approval for use of the Merritt Manufacturing Chest Clip Guard on a few of our car seats. This product makes it more difficult for a child to unbuckle and escape from their car seat harness.<br\/>· Products like the Revolve360™ Car Seat make it easier for families with a variety of mobility needs to load and unload children into a vehicle safely.<\/p>",
            "link_label": "",
            "link": "",
            "discount_verification": ""
          }
        },
        "column_i48jd8": {
          "type": "column",
          "settings": {
            "image": "shopify:\/\/shop_images\/AdobeStock_197360351.png",
            "title": "Employee-led community impact efforts",
            "text": "<p>As part of giving back, our employees select community-centric projects that help drive efforts important to them, and that make a difference in their local communities.<br\/>• Canton, MA employees sponsored 18 children for the 2023 Wonderfund Program.<br\/>• Piqua, OH employees participated in the 2023 Salvation Army Angel Tree.<br\/>• Canadian employees donated $200 worth of toys to the 2023 Canada Community Outreach. <\/p>",
            "link_label": "",
            "link": "",
            "discount_verification": ""
          }
        }
      },
      "block_order": [
        "column_RJWDbp",
        "column_i48jd8"
      ],
      "custom_css": [
        "h3 {font-size: 1.5em;}"
      ],
      "settings": {
        "title": "",
        "heading_size": "h0",
        "image_width": "full",
        "image_ratio": "adapt",
        "columns_desktop": 2,
        "column_alignment": "center",
        "background_style": "none",
        "underline": true,
        "button_label": "",
        "button_link": "",
        "color_scheme": "background-1",
        "columns_mobile": "1",
        "swipe_on_mobile": false,
        "padding_top": 36,
        "padding_bottom": 36
      }
    },
    "multicolumn_373bDw": {
      "type": "multicolumn",
      "blocks": {
        "column_VHgCX3": {
          "type": "column",
          "settings": {
            "image": "shopify:\/\/shop_images\/AdobeStock_471006097.png",
            "title": "Responsible Hiring & Inclusion",
            "text": "<p>At the center of our organization is our people. Evenflo strives to create a diverse workforce, by using inclusionary practices for hiring, that lessen bias and create a fair working environment. We do this through training, DEI forums and through ongoing celebration of customs and practices that welcome a workforce made of differences.<\/p>",
            "link_label": "",
            "link": "",
            "discount_verification": ""
          }
        },
        "column_RMxUQ3": {
          "type": "column",
          "settings": {
            "image": "shopify:\/\/shop_images\/AdobeStock_296852355_Preview_1.png",
            "title": "Sustainable Practices",
            "text": "<p>We are committed to finding ways of lessening our footprint throughout our manufacturing efforts. From making the transition to Kraft paper packaging to installing solar panels to upgrading our forklifts to electric, we hope to continue making improvements in our greener consumption efforts.<br\/>· Sustainable Forestry Initiative (SFI): This initiative aims to reduce greenhouse gas emissions, reduce waste to landfills and energize operations with clean power. This enables us to better contain and protect our products from damage and support efforts that lead to longer term healthier forests and even longer-term mitigation of climate change.<br\/>· SFI Certified Sourcing: SFI, a non-profit organization, collaborates with our diverse network to help address local and global sustainability challenges. Certified sourcing uses raw material from noncontroversial sources in the supply chain, supports logger training, recycled content, certified forests, and small family forest owners.<\/p>",
            "link_label": "",
            "link": "",
            "discount_verification": ""
          }
        }
      },
      "block_order": [
        "column_VHgCX3",
        "column_RMxUQ3"
      ],
      "custom_css": [
        "h3 {font-size: 1.5em;}"
      ],
      "settings": {
        "title": "",
        "heading_size": "h0",
        "image_width": "full",
        "image_ratio": "adapt",
        "columns_desktop": 3,
        "column_alignment": "center",
        "background_style": "none",
        "underline": true,
        "button_label": "",
        "button_link": "",
        "color_scheme": "background-1",
        "columns_mobile": "1",
        "swipe_on_mobile": false,
        "padding_top": 36,
        "padding_bottom": 36
      }
    },
    "divider_m3mUrA": {
      "type": "divider",
      "settings": {
        "divider_spacing": 35,
        "divider_border": false,
        "css_class": "",
        "custom_css": ""
      }
    },
    "image_with_text_NaBrd3": {
      "type": "image-with-text",
      "blocks": {
        "text_wrbFy6": {
          "type": "text",
          "settings": {
            "text": "<p>REVOLVE360™ SLIM 2-IN-1 ROTATIONAL CAR SEAT<\/p>",
            "text_style": "body"
          }
        },
        "heading_yRJgDi": {
          "type": "heading",
          "settings": {
            "heading": "MAXIMIZE SPACE IN YOUR BACKSEAT",
            "heading_size": "h1"
          }
        },
        "caption_JgLDaJ": {
          "type": "caption",
          "settings": {
            "caption": "Fit more of what you love into your backseat with a streamlined 16.7 in. footprint and one-hand, 360° rotation",
            "text_style": "subtitle",
            "text_size": "small"
          }
        },
        "button_ejqzND": {
          "type": "button",
          "settings": {
            "button_label": "SHOP STYLES",
            "button_link": "https:\/\/www.evenflo.com\/search?q=REVOLVE360+SLIM&options%5Bprefix%5D=last&filter.v.m.sf_variants.refinement_color=Black&filter.v.m.sf_variants.refinement_color=Blue&filter.v.m.sf_variants.refinement_color=Gray&filter.v.price.gte=&filter.v.price.lte=&filter.p.product_type=Convertible+Car+Seat&filter.p.m.sf_products.platform=Revolve360+Slim&sort_by=relevance"
          }
        }
      },
      "block_order": [
        "text_wrbFy6",
        "heading_yRJgDi",
        "caption_JgLDaJ",
        "button_ejqzND"
      ],
      "disabled": true,
      "settings": {
        "image": "shopify:\/\/shop_images\/368127470_Core_Revolve360_Slim_2_in_1_Rotational_Convertible_Car_Seat_Canton_Triple_0088-_1.jpg",
        "height": "adapt",
        "desktop_image_width": "medium",
        "layout": "image_first",
        "desktop_content_position": "middle",
        "desktop_content_alignment": "left",
        "content_layout": "no-overlap",
        "color_scheme": "background-1",
        "image_behavior": "none",
        "mobile_content_alignment": "left",
        "padding_top": 0,
        "padding_bottom": 48
      }
    },
    "image_with_text_BFt4TM": {
      "type": "image-with-text",
      "blocks": {
        "text_hefEqh": {
          "type": "text",
          "settings": {
            "text": "<p>SHYFT™ DUALRIDE™ INFANT CAR SEAT AND STROLLER COMBO<\/p>",
            "text_style": "body"
          }
        },
        "heading_fq86PB": {
          "type": "heading",
          "settings": {
            "heading": "THE ONCE PIECE OF BABY GEAR THAT DOES IT ALL",
            "heading_size": "h1"
          }
        },
        "caption_pN3XWT": {
          "type": "caption",
          "settings": {
            "caption": "This single piece of baby gear transforms from infant car seat to stroller and back again with ease, streamlining life on the go",
            "text_style": "subtitle",
            "text_size": "small"
          }
        },
        "button_QAtNgm": {
          "type": "button",
          "settings": {
            "button_label": "SHOP STYLES",
            "button_link": "shopify:\/\/collections\/car-seat-stroller-combos"
          }
        }
      },
      "block_order": [
        "text_hefEqh",
        "heading_fq86PB",
        "caption_pN3XWT",
        "button_QAtNgm"
      ],
      "settings": {
        "image": "shopify:\/\/shop_images\/37312473_Boone_Shyft_Dual_Ride_1333-_1.jpg",
        "height": "adapt",
        "desktop_image_width": "medium",
        "layout": "text_first",
        "desktop_content_position": "middle",
        "desktop_content_alignment": "left",
        "content_layout": "no-overlap",
        "color_scheme": "background-1",
        "image_behavior": "none",
        "mobile_content_alignment": "left",
        "padding_top": 0,
        "padding_bottom": 48
      }
    },
    "image_with_text_mTYnR6": {
      "type": "image-with-text",
      "blocks": {
        "text_qq9yWU": {
          "type": "text",
          "settings": {
            "text": "<p>PIVOT XPLORE™ DREAMZ™ ALL-TERRAIN STROLLER WAGON WITH BASSINET<\/p>",
            "text_style": "body"
          }
        },
        "heading_KbeYKR": {
          "type": "heading",
          "settings": {
            "heading": "ADVENTURE THEN NAP",
            "heading_size": "h1"
          }
        },
        "caption_Kf7JNw": {
          "type": "caption",
          "settings": {
            "caption": "Includes a naptime-on-the-go bassinet insert (for children 6 months to 33 lb) to let your little one take a break from the action",
            "text_style": "subtitle",
            "text_size": "small"
          }
        },
        "button_w88nDD": {
          "type": "button",
          "settings": {
            "button_label": "SHOP STYLES",
            "button_link": "shopify:\/\/products\/pivot-xplore-dreamz-stroller-wagon"
          }
        }
      },
      "block_order": [
        "text_qq9yWU",
        "heading_KbeYKR",
        "caption_Kf7JNw",
        "button_w88nDD"
      ],
      "settings": {
        "image": "shopify:\/\/shop_images\/18912482_JetSetter_692-_4.jpg",
        "height": "adapt",
        "desktop_image_width": "medium",
        "layout": "image_first",
        "desktop_content_position": "middle",
        "desktop_content_alignment": "left",
        "content_layout": "no-overlap",
        "color_scheme": "background-1",
        "image_behavior": "none",
        "mobile_content_alignment": "left",
        "padding_top": 0,
        "padding_bottom": 48
      }
    },
    "evenflo_collection_image_banner_6yhkMU": {
      "type": "evenflo-collection-image-banner",
      "blocks": {
        "text_YQ9fgD": {
          "type": "text",
          "settings": {
            "text": "<strong>PIVOT TROOP™<\/strong> CHILD AND PET TRAVEL SYSTEM",
            "text_style": "body"
          }
        },
        "heading_ey8N6e": {
          "type": "heading",
          "settings": {
            "heading": "BRING YOUR WHOLE TROOP",
            "heading_size": "h1",
            "heading_color": "black"
          }
        },
        "buttons_VX8kib": {
          "type": "buttons",
          "settings": {
            "button_label_1": "Button label",
            "button_link_1": "",
            "button_style_secondary_1": false,
            "button_label_2": "",
            "button_link_2": "",
            "button_style_secondary_2": false
          }
        }
      },
      "block_order": [
        "text_YQ9fgD",
        "heading_ey8N6e",
        "buttons_VX8kib"
      ],
      "disabled": true,
      "settings": {
        "image": "shopify:\/\/shop_images\/troop-header.png",
        "image_2": "shopify:\/\/shop_images\/troop-header.png",
        "image_overlay_opacity": 0,
        "image_height": "medium",
        "desktop_content_position": "middle-center",
        "show_text_box": true,
        "desktop_content_alignment": "center",
        "color_scheme": "background-1",
        "image_behavior": "none",
        "mobile_content_alignment": "center",
        "stack_images_on_mobile": true,
        "show_text_below": true
      }
    },
    "evenflo_video_home_J93MtL": {
      "type": "evenflo-video-home",
      "blocks": {
        "image_8QHEDf": {
          "type": "image",
          "settings": {
            "image": "shopify:\/\/shop_images\/troop-top-2.jpg",
            "media_shape": "square"
          }
        }
      },
      "block_order": [
        "image_8QHEDf"
      ],
      "disabled": true,
      "settings": {
        "title": "<p>Bring your whole troop<\/p>",
        "heading_tag": "h2",
        "font_size_desktop": 40,
        "font_size_mobile": 30,
        "description": "PIVOT TROOP™ CHILD AND PET TRAVEL SYSTEM",
        "link_text": "Shop Now",
        "link_url": "shopify:\/\/products\/pivot-troop-child-and-pet-car-seat-and-stroller-travel-system",
        "img_submark_rotate": false,
        "img_submark_hide": false,
        "layout": "center",
        "media_mobile_hide": true,
        "text_container_shape": "square",
        "color_text": "#000000",
        "color_text_container": "rgba(0,0,0,0)",
        "color_bg": "#ffffff",
        "color_border": "#ffffff",
        "btn_shape": "square",
        "color_btn_fill": "#000000",
        "color_btn_border": "#000000",
        "color_btn_text": "#ffffff",
        "color_btn_fill_hover": "#000000",
        "color_btn_border_hover": "#000000",
        "color_btn_text_hover": "#ffffff",
        "font_size_btn_desktop": 18,
        "font_size_btn_mobile": 14,
        "css_class": "",
        "custom_css": ""
      }
    },
    "main": {
      "type": "main-page",
      "disabled": true,
      "settings": {
        "padding_top": 28,
        "padding_bottom": 28
      }
    }
  },
  "order": [
    "image_banner_j8bDQb",
    "divider_7njMcJ",
    "rich_text_xFi7Um",
    "multicolumn_f9LYpV",
    "multicolumn_373bDw",
    "divider_m3mUrA",
    "image_with_text_NaBrd3",
    "image_with_text_BFt4TM",
    "image_with_text_mTYnR6",
    "evenflo_collection_image_banner_6yhkMU",
    "evenflo_video_home_J93MtL",
    "main"
  ]
}
